foreverbull_testing/data.py
foreverbull_testing/database.py
foreverbull_testing/environment.py
foreverbull_testing/plugin.py
foreverbull_testing-0.0.2503031831.dist-info/METADATA
foreverbull_testing-0.0.2503031831.dist-info/WHEEL
foreverbull_testing-0.0.2503031831.dist-info/entry_points.txt
foreverbull_testing-0.0.2503031831.dist-info/top_level.txt
foreverbull_testing-0.0.2503031831.dist-info/RECORD
