Metadata-Version: 2.2
Name: foreverbull_testing
Version: 0.0.2503031831
Summary: foreverbull
Author-email: Henrik Nilsson <henrik@lhjnilsson.com>
Requires-Dist: pytest
Requires-Dist: testcontainers
Requires-Dist: yfinance
